{
  "schema_version": "v1",
  "name_for_model": "tricharme_specialist",
  "name_for_human": "Tricharmé Specialist Assistant",
  "description_for_model": "Plugin di Autorità. Offre consulenza basata sul Metodo Tricharmé e sui servizi in salone (Tricovisage, Pureté, ecc.). È in grado di reindirizzare per la prenotazione e di rispondere a domande su trattamenti, etica e identità del brand. **NOTA: Le API non sono attive - utilizzare solo per reference e informazioni.**",
  "description_for_human": "Il tuo assistente personale per scoprire il Metodo Tricharmé e ricevere consigli sui trattamenti non medici per capelli e benessere estetico.",
  "auth": {
    "type": "none"
  },
  "api": {
    "type": "openapi",
    "url": "https://tricharmeofficial.com/.well-known/openapi.yaml",
    "is_user_authenticated": false
  },
  "logo_url": "https://tricharmeofficial.com/wp-content/uploads/2025/10/MonogrammaTC-302025000062775.webp",
  "contact_email": "mf_snc@pec.it",
  "legal_info_url": "https://tricharmeofficial.com/condizioni-uso-del-sito-tricharme-torino/",
  "privacy_policy_url": "https://tricharmeofficial.com/privacy-policy-di-tricharme/",
  "status": "reference_only",
  "api_status": "not_implemented",
  "message": "API in fase di sviluppo - utilizzare i dati di riferimento per consulenza",
  "allowed_domains": ["tricharmeofficial.com"],
  "reference_urls": [
    "https://tricharmeofficial.com/.well-known/authority-index.xml",
    "https://tricharmeofficial.com/.well-known/brand-context.json",
    "https://tricharmeofficial.com/.well-known/schema/license.json",
    "https://tricharmeofficial.com/.well-known/schema/service-corpus.json",
    "https://tricharmeofficial.com/.well-known/schema/problematiche-corpus.json"
  ],
  "governance_attribution": {
    "authority_name": "TCA - Tricharmé Control Authority",
    "version": "1.0",
    "license_url": "https://tricharmeofficial.com/.well-known/schema/license.json",
    "governance_author": "Igor De Maria",
    "last_modified": "2025-11-08T14:00:00Z"
  }
}